domain2vec/__init__.py
domain2vec-0.1.dist-info/LICENSE
domain2vec-0.1.dist-info/METADATA
domain2vec-0.1.dist-info/WHEEL
domain2vec-0.1.dist-info/top_level.txt
domain2vec-0.1.dist-info/RECORD
