Metadata-Version: 2.1
Name: domain2vec
Version: 0.1
Summary: UNKNOWN
Home-page: UNKNOWN
Author: Kowsher
Author-email: ga.kowsher@gmail.com
License: MIT
Platform: UNKNOWN
Classifier: Programming Language :: Python :: 3
Classifier: License :: OSI Approved :: MIT License
Classifier: Operating System :: OS Independent
